pygpi/entry.py
pygpi/__init__.py
cocotb/_sim_versions.py
cocotb/runner.py
cocotb/result.py
cocotb/decorators.py
cocotb/triggers.py
cocotb/log.py
cocotb/queue.py
cocotb/_deprecation.py
cocotb/memdebug.py
cocotb/xunit_reporter.py
cocotb/regression.py
cocotb/wavedrom.py
cocotb/ANSI.py
cocotb/_py_compat.py
cocotb/__init__.py
cocotb/_version.py
cocotb/config.py
cocotb/handle.py
cocotb/outcomes.py
cocotb/ipython_support.py
cocotb/binary.py
cocotb/simulator.cpython-310-x86_64-linux-gnu.so
cocotb/task.py
cocotb/scheduler.py
cocotb/clock.py
cocotb/utils.py
cocotb/libs/libpygpilog.so
cocotb/libs/libcocotbutils.so
cocotb/libs/libembed.so
cocotb/libs/libgpilog.so
cocotb/libs/libcocotbvpi_verilator.so
cocotb/libs/libcocotbvpi_ius.so
cocotb/libs/libcocotbfli_modelsim.so
cocotb/libs/libcocotbvpi_aldec.so
cocotb/libs/libcocotbvpi_icarus.vpl
cocotb/libs/libcocotbvhpi_aldec.so
cocotb/libs/libcocotbvpi_vcs.so
cocotb/libs/libgpi.so
cocotb/libs/libcocotbvhpi_modelsim.so
cocotb/libs/libcocotbvpi_ghdl.so
cocotb/libs/libcocotb.so
cocotb/libs/libcocotbvhpi_ius.so
cocotb/libs/libcocotbvpi_modelsim.so
cocotb/types/logic_array.py
cocotb/types/__init__.py
cocotb/types/array.py
cocotb/types/logic.py
cocotb/types/range.py
cocotb/_vendor/__init__.py
cocotb/_vendor/distutils_version.py
rapidstream_cocotb-1.8.1.dev0.dist-info/LICENSE
rapidstream_cocotb-1.8.1.dev0.dist-info/top_level.txt
rapidstream_cocotb-1.8.1.dev0.dist-info/WHEEL
rapidstream_cocotb-1.8.1.dev0.dist-info/entry_points.txt
rapidstream_cocotb-1.8.1.dev0.dist-info/METADATA
rapidstream_cocotb-1.8.1.dev0.dist-info/RECORD
