Metadata-Version: 2.1
Name: rapidstream-cocotb
Version: 1.8.1.dev0
Summary: RapidStream-specific version of cocotb.  cocotb contributors has all rights over this project.  cocotb is a coroutine based cosimulation library for writing VHDL and Verilog testbenches in Python.
Home-page: https://www.cocotb.org
Author: Chris Higgs, Stuart Hodgson
Maintainer: cocotb contributors
Maintainer-email: cocotb@lists.librecores.org
License: BSD
Project-URL: Bug Tracker, https://github.com/rapidstream-da/cocotb/issues
Project-URL: Source Code, https://github.com/rapidstream-da/cocotb
Project-URL: Documentation, https://docs.cocotb.org
Platform: any
Classifier: Programming Language :: Python :: 3
Classifier: Programming Language :: Python :: 3.6
Classifier: Programming Language :: Python :: 3.7
Classifier: Programming Language :: Python :: 3.8
Classifier: Programming Language :: Python :: 3.9
Classifier: Programming Language :: Python :: 3.10
Classifier: Programming Language :: Python :: 3.11
Classifier: License :: OSI Approved :: BSD License
Classifier: Topic :: Scientific/Engineering :: Electronic Design Automation (EDA)
Classifier: Framework :: cocotb
Requires-Python: >=3.6
License-File: LICENSE
Requires-Dist: find_libpython
Provides-Extra: bus
Requires-Dist: cocotb_bus; extra == "bus"
